full_width/__init__.py
full_width/jupyter/full_width.js
full_width/jupyter/full_width.yaml
full_width/jupyter/icon.png
full_width/jupyter/readme.md
jupyter_full_width-1.2.0.dist-info/DESCRIPTION.rst
jupyter_full_width-1.2.0.dist-info/METADATA
jupyter_full_width-1.2.0.dist-info/RECORD
jupyter_full_width-1.2.0.dist-info/WHEEL
jupyter_full_width-1.2.0.dist-info/metadata.json
jupyter_full_width-1.2.0.dist-info/top_level.txt
