Metadata-Version: 2.0
Name: jupyter-full-width
Version: 1.2.0
Summary: Add a button to allow jupyter to use the full browser width
Home-page: https://github.com/JoaoFelipe/JupyterFullWidth
Author: Joao Felipe Pimentel
Author-email: joaofelipenp@gmail.com
License: UNKNOWN
Platform: UNKNOWN
